NoWebsocket/__init__.py
NoWebsocket/application.py
NoWebsocket/connection.py
NoWebsocket/constants.py
NoWebsocket/exceptions.py
NoWebsocket/protocol.py
NoWebsocket/router.py
NoWebsocket/server.py
NoWebsocket/utils.py
blueprints/EchoBp.py
blueprints/__init__.py
nowebsocket-2.2.1.dist-info/licenses/LICENSE
nowebsocket-2.2.1.dist-info/METADATA
nowebsocket-2.2.1.dist-info/WHEEL
nowebsocket-2.2.1.dist-info/top_level.txt
nowebsocket-2.2.1.dist-info/RECORD
