Metadata-Version: 2.4
Name: NoWebsocket
Version: 2.2.1
Summary: 一个面向对象的Python WebSocket服务端框架，支持零配置多文件路由管理，实现高效、模块化的实时通信开发。
Home-page: https://github.com/dzy-china/NoWebsocket
Author: dzy
Author-email: 1129881228@qq.com
Classifier: Programming Language :: Python :: 3
Classifier: License :: OSI Approved :: MIT License
Classifier: Operating System :: OS Independent
Requires-Python: >=3.7
License-File: LICENSE
Dynamic: author
Dynamic: author-email
Dynamic: classifier
Dynamic: description
Dynamic: description-content-type
Dynamic: home-page
Dynamic: license-file
Dynamic: requires-python
Dynamic: summary
